Workbook

Sheet Search
C11: Ticker | D11: Sector | E11: Index
C12: cnp | D12: =VLOOKUP(C12,Tickers!A:B,2,FALSE) -> Utilities | E12: =VLOOKUP(D12,Match_Sector!A1:B20,2,FALSE) -> XLU (Utilities)

Sheet Tickers
A1: Symbol | B1: Sector | C1: Description | D1: Price | E1: Price - Currency | F1: Price Change % 1 day | G1: Volume 1 day | H1: Relative Volume 1 day | I1: Market capitalization | J1: Market capitalization - Currency | K1: Price to earnings ratio | L1: Earnings per share diluted, Trailing 12 months | M1: Earnings per share diluted, Trailing 12 months - Currency | N1: Earnings per share diluted growth %, TTM YoY | O1: Dividend yield %, Trailing 12 months | P1: Analyst Rating
A2: A | B2: Health technology | C2: Agilent Technologies, Inc, | D2: 140.25 | E2: USD | F2: 1.6672708 | G2: 686264 | H2: 0.36478252 | I2: 3.9760716e+10 | J2: USD | K2: 30.692636 | L2: 4.5695 | M2: USD | N2: 3.2212157 | O2: 0.71910112 | P2: Buy
A3: AA | B3: Non-energy minerals | C3: Alcoa Corporation | D3: 59.85 | E3: USD | F3: 5.8542625 | G3: 2872398 | H3: 0.5338615 | I3: 1.5498997e+10 | J3: USD | K3: 13.593313 | L3: 4.4029 | M3: USD | O3: 0.70746374 | P3: Buy
A4: AACB | B4: Finance | C4: Artius II Acquisition Inc, | D4: 10.29 | E4: USD | F4: -0.097087379 | G4: 1399 | H4: 0.014722937 | I4: 284775741 | J4: USD | O4: 0 | P4: Neutral
A5: AAL | B5: Transportation | C5: American Airlines Group, Inc, | D5: 15.79 | E5: USD | F5: 2.002584 | G5: 14754574 | H5: 0.33120098 | I5: 1.0422765e+10 | J5: USD | K5: 18.982929 | L5: 0.8318 | M5: USD | N5: 158.32298 | O5: 0 | P5: Buy
A6: AAM | B6: Finance | C6: AA Mission Acquisition Corp, | D6: 10.65 | E6: USD | F6: 0.093984962 | G6: 219 | H6: 0.0066464945 | I6: 4.6832311e+08 | J6: USD | K6: 32.728949 | L6: 0.3254 | M6: USD | O6: 0 | P6: Neutral
A7: AAMI | B7: Finance | C7: Acadian Asset Management Inc, | D7: 50.32 | E7: USD | F7: 6.2051499 | G7: 40799 | H7: 0.21884095 | I7: 1.796883e+09 | J7: USD | K7: 21.228485 | L7: 2.3704 | M7: USD | N7: 44.307805 | O7: 0.084423808 | P7: Neutral
A8: AAOI | B8: Electronic technology | C8: Applied Optoelectronics, Inc, | D8: 36.83 | E8: USD | F8: -6.9949495 | G8: 3068444 | H8: 0.62960913 | I8: 2.5147483e+09 | J8: USD | L8: -3.2256 | M8: USD | N8: -56.112671 | O8: 0 | P8: Buy
A9: AAON | B9: Producer manufacturing | C9: AAON, Inc, | D9: 82.73 | E9: USD | F9: 4.4702614 | G9: 242466 | H9: 0.2364416 | I9: 6.7535857e+09 | J9: USD | K9: 68.678399 | L9: 1.2046 | M9: USD | N9: -47.273046 | O9: 0.50511428 | P9: Strong buy
A10: AAP | B10: Retail trade | C10: Advance Auto Parts Inc, | D10: 39.66 | E10: USD | F10: 1.9799434 | G10: 620171 | H10: 0.29039994 | I10: 2.3804823e+09 | J10: USD | L10: -6.3128 | M10: USD | N10: -966.42877 | O10: 2.5713551 | P10: Neutral
A11: AAPG | B11: Health technology | C11: Ascentage Pharma Group International Unsponsored ADR | D11: 26.7 | E11: USD | F11: 1.2514221 | G11: 478 | H11: 0.13278884 | I11: 2.4187896e+09 | J11: USD | L11: -2.0128 | M11: USD | N11: -189.56985 | O11: 0 | P11: Strong buy
A12: AAPL | B12: Electronic technology | C12: Apple Inc, | D12: 268.97 | E12: USD | F12: -0.75273975 | G12: 13645057 | H12: 0.33047289 | I12: 3.9743957e+12 | J12: USD | K12: 36.058343 | L12: 7.4593 | M12: USD | N12: 22.889998 | O12: 0.38005978 | P12: Buy
A13: AARD | B13: Health technology | C13: Aardvark Therapeutics, Inc, | D13: 13.01 | E13: USD | F13: -1.3646702 | G13: 80995 | H13: 0.33251636 | I13: 2.8327025e+08 | J13: USD | L13: -2.2465 | M13: USD | N13: 31.299694 | O13: 0 | P13: Strong buy
A14: AAT | B14: Finance | C14: American Assets Trust, Inc, | D14: 18.77 | E14: USD | F14: -0.053248136 | G14: 61230 | H14: 0.12408368 | I14: 1148444783 | J14: USD | K14: 18.476228 | L14: 1.0159 | M14: USD | N14: 5.0568769 | O14: 7.2417465 | P14: Neutral
A15: AAUC | B15: Non-energy minerals | C15: Allied Gold Corporation | D15: 23.87 | E15: USD | F15: 3.2886196 | G15: 318894 | H15: 0.44161832 | I15: 2.9609672e+09 | J15: USD | L15: -0.338896 | M15: USD | N15: 71.660821 | O15: 0 | P15: Strong buy
A16: AB | B16: Finance | C16: AllianceBernstein Holding L,P, | D16: 39.445 | E16: USD | F16: 2.0833333 | G16: 55417 | H16: 0.3706027 | I16: 3.5892287e+09 | J16: USD | K16: 12.997133 | L16: 3.0349 | M16: USD | N16: -12.920349 | O16: 8.9803313 | P16: Neutral
A17: ABBV | B17: Health technology | C17: AbbVie Inc, | D17: 218.84 | E17: USD | F17: -4.5658715 | G17: 2198322 | H17: 0.45614473 | I17: 3.8677445e+11 | J17: USD | K17: 165.12488 | L17: 1.3253 | M17: USD | N17: -53.780428 | O17: 2.8607562 | P17: Buy
A18: ABCB | B18: Finance | C18: Ameris Bancorp | D18: 76.345 | E18: USD | F18: 3.1968099 | G18: 63012 | H18: 0.14023836 | I18: 5.2155196e+09 | J18: USD | K18: 13.209163 | L18: 5.7797 | M18: USD | N18: 20.810602 | O18: 1.0813733 | P18: Buy
A19: ABEO | B19: Health technology | C19: Abeona Therapeutics Inc, | D19: 5.2 | E19: USD | F19: -2.0715631 | G19: 323638 | H19: 0.33168236 | I19: 2.8179507e+08 | J19: USD | K19: 4.4623702 | L19: 1.1653 | M19: USD | O19: 0 | P19: Strong buy
A20: ABG | B20: Retail trade | C20: Asbury Automotive Group Inc | D20: 240.5 | E20: USD | F20: 2.4450503 | G20: 64508 | H20: 0.31751251 | I20: 4.6754544e+09 | J20: USD | K20: 8.4370867 | L20: 28.5051 | M20: USD | N20: 61.15502 | O20: 0 | P20: Neutral
A21: ABM | B21: Commercial services | C21: ABM Industries Incorporated | D21: 43.63 | E21: USD | F21: 2.2258669 | G21: 130774 | H21: 0.1286185 | I21: 2.6255497e+09 | J21: USD | K21: 16.860533 | L21: 2.5877 | M21: USD | N21: 102.54383 | O21: 2.4835989 | P21: Buy
A22: ABNB | B22: Consumer services | C22: Airbnb, Inc, | D22: 136.52 | E22: USD | F22: 2.6388993 | G22: 1144134 | H22: 0.29883709 | I22: 8.403485e+10 | J22: USD | K22: 32.300194 | L22: 4.2266 | M22: USD | N22: 48.442384 | O22: 0 | P22: Neutral
A23: ABR | B23: Finance | C23: Arbor Realty Trust Inc | D23: 8.115 | E23: USD | F23: 2.0754717 | G23: 956352 | H23: 0.24668774 | I23: 1555899611 | J23: USD | K23: 10.370607 | L23: 0.7825 | M23: USD | N23: -39.668466 | O23: 16.72956 | P23: Sell
A24: ABR/PD | B24: Finance | C24: Arbor Realty Trust 6,375% Series D Cumulative Redeemable Preferred Stock, Liquidation Preference $25,00 per Share | D24: 17.385 | E24: USD | F24: 0.7826087 | G24: 4421 | H24: 0.17473065 | I24: 1555899611 | J24: USD | K24: 22.217252 | L24: 0.7825 | M24: USD | N24: -39.668466 | O24: 16.72956 | P24: Neutral
A25: ABR/PE | B25: Finance | C25: Arbor Realty Trust 6,25% Series E Cumulative Redeemable Preferred Stock | D25: 17.35 | E25: USD | F25: 0.28901734 | G25: 6046 | H25: 0.36780406 | I25: 1555899611 | J25: USD | K25: 22.172524 | L25: 0.7825 | M25: USD | N25: -39.668466 | O25: 16.72956 | P25: Neutral
A26: ABR/PF | B26: Finance | C26: Arbor Realty Trust 6,25% Series F Fixed-to-Floating Rate Cumulative Redeemable Preferred Stock, Liquidation Preference $25,00 per share | D26: 22 | E26: USD | F26: 0.54844607 | G26: 1417 | H26: 0.069123637 | I26: 1555899611 | J26: USD | K26: 28.115016 | L26: 0.7825 | M26: USD | N26: -39.668466 | O26: 16.72956 | P26: Neutral
A27: ABT | B27: Health technology | C27: Abbott Laboratories | D27: 124.655 | E27: USD | F27: 0.37442628 | G27: 1679609 | H27: 0.30568805 | I27: 2.1675909e+11 | J27: USD | K27: 15.635622 | L27: 7.9725 | M27: USD | N27: 142.45051 | O27: 1.900314 | P27: Buy
A28: ABTS | B28: Technology services | C28: Abits Group Inc | D28: 5.19 | E28: USD | F28: 0.77669903 | G28: 465 | H28: 0.10814205 | I28: 12300275 | J28: USD | L28: -0.5275 | M28: USD | N28: 86.254072 | O28: 0 | P28: Neutral
A29: ABVX | B29: Health technology | C29: Abivax SA Sponsored ADR | D29: 121.74 | E29: USD | F29: -8.9930478 | G29: 782568 | H29: 0.45554033 | I29: 1.0503443e+10 | J29: USD | O29: 0 | P29: Strong buy
A30: ABX | B30: Finance | C30: Abacus Global Management, Inc, | D30: 7.895 | E30: USD | F30: -0.31565657 | G30: 145339 | H30: 0.0084344601 | I30: 7.7175878e+08 | J30: USD | K30: 101.08835 | L30: 0.0781 | M30: USD | O30: 2.5252525 | P30: Strong buy
A31: ABXL | B31: Finance | C31: Abacus Global Management, Inc, 9,875% Fixed Rate Senior Notes due 2028 | D31: 25.59 | E31: USD | F31: 0.35294118 | G31: 7911 | H31: 2.1245569 | I31: 774202606 | J31: USD | K31: 327.65685 | L31: 0.0781 | M31: USD | O31: 2.5252525 | P31: Neutral
A32: ACA | B32: Non-energy minerals | C32: Arcosa, Inc, | D32: 109.15 | E32: USD | F32: 2.2099448 | G32: 29602 | H32: 0.15040146 | I32: 5.3532645e+09 | J32: USD | K32: 36.135205 | L32: 3.0206 | M32: USD | N32: 14.921625 | O32: 0.18728345 | P32: Strong buy
A33: ACAD | B33: Health technology | C33: ACADIA Pharmaceuticals Inc, | D33: 25.64 | E33: USD | F33: -2.472423 | G33: 307228 | H33: 0.23820233 | I33: 4.3378217e+09 | J33: USD | K33: 16.496172 | L33: 1.5543 | M33: USD | N33: 101.20388 | O33: 0 | P33: Buy
A34: ACEL | B34: Consumer services | C34: Accel Entertainment, Inc, | D34: 11.38 | E34: USD | F34: 0.087950748 | G34: 48557 | H34: 0.1012522 | I34: 9.4690642e+08 | J34: USD | K34: 22.525732 | L34: 0.5052 | M34: USD | N34: 0.73778664 | O34: 0 | P34: Strong buy
A35: ACET | B35: Health technology | C35: Adicet Bio, Inc, | D35: 8.2 | E35: USD | F35: -7.0294785 | G35: 109992 | H35: 0.44490407 | I35: 78543484 | J35: USD | L35: -20.2173 | M35: USD | N35: 25.887489 | O35: 0 | P35: Strong buy
A36: ACFN | B36: Electronic technology | C36: Acorn Energy, Inc, | D36: 18.6802 | E36: USD | F36: 22.73456 | G36: 35936 | H36: 0.44405232 | I36: 46786916 | J36: USD | K36: 7.0467388 | L36: 2.6509 | M36: USD | N36: 481.21026 | O36: 0 | P36: Neutral
A37: ACGL | B37: Finance | C37: Arch Capital Group Ltd, | D37: 94.99 | E37: USD | F37: 1.2039207 | G37: 433416 | H37: 0.21048823 | I37: 3.4445839e+10 | J37: USD | K37: 8.889284 | L37: 10.6859 | M37: USD | N37: -28.252214 | O37: 0 | P37: Buy
A38: ACGLN | B38: Finance | C38: Arch Capital Group Ltd, - Depositary Shares, each Representing a 1/1,000th Interest in a 4,550% Non-Cumulative Preferred Share, Series G | D38: 16.99 | E38: USD | F38: 0.29515939 | G38: 34193 | H38: 0.50881078 | I38: 3.4036072e+10 | J38: USD | K38: 1.5899456 | L38: 10.6859 | M38: USD | N38: -28.252214 | O38: 0 | P38: Neutral
A39: ACGLO | B39: Finance | C39: Arch Capital Group Ltd, - Depositary Shares Each Representing 1/1,000th Interest in a Share of5,45% Non-Cumulative Preferred Shares, Series F | D39: 20.72 | E39: USD | F39: 0.72921731 | G39: 12636 | H39: 0.29765382 | I39: 3.4036072e+10 | J39: USD | K39: 1.9390037 | L39: 10.6859 | M39: USD | N39: -28.252214 | O39: 0 | P39: Neutral
A40: ACHC | B40: Health services | C40: Acadia Healthcare Company, Inc, | D40: 14.05 | E40: USD | F40: -1.6794962 | G40: 728174 | H40: 0.31341144 | I40: 1.2962272e+09 | J40: USD | K40: 11.918901 | L40: 1.1788 | M40: USD | N40: -61.353354 | O40: 0 | P40: Buy
A41: ACHR | B41: Electronic technology | C41: Archer Aviation Inc, | D41: 8.5749 | E41: USD | F41: 5.4723247 | G41: 18205995 | H41: 0.63582772 | I41: 6.2818994e+09 | J41: USD | L41: -1.1844 | M41: USD | N41: 11.141121 | O41: 0 | P41: Buy
A42: ACHV | B42: Health technology | C42: Achieve Life Sciences, Inc, | D42: 5.15 | E42: USD | F42: 3.6217304 | G42: 346379 | H42: 0.57004377 | I42: 2.7415504e+08 | J42: USD | L42: -1.3777 | M42: USD | N42: -22.060778 | O42: 0 | P42: Strong buy
A43: ACI | B43: Retail trade | C43: Albertsons Companies, Inc, | D43: 16.99 | E43: USD | F43: -1.8486424 | G43: 2355242 | H43: 0.29261948 | I43: 9.3327341e+09 | J43: USD | K43: 10.052065 | L43: 1.6902 | M43: USD | N43: -1.457556 | O43: 3.4662045 | P43: Buy
A44: ACIC | B44: Finance | C44: American Coastal Insurance Corporation | D44: 11.335 | E44: USD | F44: -0.39543058 | G44: 38463 | H44: 0.28314179 | I44: 5.5275469e+08 | J44: USD | K44: 6.5425685 | L44: 1.7325 | M44: USD | N44: -1.5960468 | O44: 0 | P44: Buy
A45: ACIW | B45: Technology services | C45: ACI Worldwide, Inc, | D45: 46.62 | E45: USD | F45: 2.0801401 | G45: 231770 | H45: 0.37008543 | I45: 4.8059626e+09 | J45: USD | K45: 18.856172 | L45: 2.4724 | M45: USD | N45: 17.186463 | O45: 0 | P45: Strong buy
A46: ACLS | B46: Producer manufacturing | C46: Axcelis Technologies, Inc, | D46: 90.445 | E46: USD | F46: 5.0220622 | G46: 146137 | H46: 0.43128348 | I46: 2.8037166e+09 | J46: USD | K46: 21.378259 | L46: 4.2307 | M46: USD | N46: -37.387894 | O46: 0 | P46: Buy
A47: ACLX | B47: Health technology | C47: Arcellx, Inc, | D47: 60.95 | E47: USD | F47: -3.773287 | G47: 250049 | H47: 0.29846476 | I47: 3.5243041e+09 | J47: USD | L47: -3.9185 | M47: USD | N47: -425.40896 | O47: 0 | P47: Strong buy
A48: ACM | B48: Industrial services | C48: AECOM | D48: 98.3745 | E48: USD | F48: 2.0482365 | G48: 186104 | H48: 0.14746152 | I48: 1.2969038e+10 | J48: USD | K48: 21.652653 | L48: 4.5433 | M48: USD | N48: 53.801625 | O48: 1.0788382 | P48: Buy
A49: ACMR | B49: Producer manufacturing | C49: ACM Research, Inc, | D49: 45.29 | E49: USD | F49: 0.91354724 | G49: 529674 | H49: 0.44129861 | I49: 2.9382546e+09 | J49: USD | K49: 26.474543 | L49: 1.7107 | M49: USD | N49: 28.943996 | O49: 0 | P49: Strong buy
A50: ACN | B50: Technology services | C50: Accenture plc | D50: 264.3101 | E50: USD | F50: 1.6772841 | G50: 946643 | H50: 0.26989655 | I50: 1.626318e+11 | J50: USD | K50: 21.852117 | L50: 12.0954 | M50: USD | N50: 1.3906702 | O50: 2.3350644 | P50: Buy
A51: ACNB | B51: Finance | C51: ACNB Corporation | D51: 48.845 | E51: USD | F51: 3.3756614 | G51: 7996 | H51: 0.34226668 | I51: 5.0724611e+08 | J51: USD | K51: 14.907676 | L51: 3.2765 | M51: USD | N51: -4.7556757 | O51: 2.9206349 | P51: Buy
A52: ACNT | B52: Process industries | C52: Ascent Industries Co, | D52: 16.12 | E52: USD | F52: 0.373599 | G52: 24074 | H52: 0.40780166 | I52: 1.5096081e+08 | J52: USD | K52: 173.7069 | L52: 0.0928 | M52: USD | O52: 0 | P52: Neutral
A53: ACOG | B53: Finance | C53: Alpha Cognition Inc, | D53: 6.4 | E53: USD | F53: -1.5384615 | G53: 3335 | H53: 0.031292605 | I53: 1.3914946e+08 | J53: USD | L53: -1.3667 | M53: USD | N53: 52.515461 | O53: 0 | P53: Strong buy
A54: ACON | B54: Technology services | C54: Aclarion, Inc, | D54: 5.27 | E54: USD | F54: 5.8232932 | G54: 18507 | H54: 0.16120462 | I54: 3538125.6 | J54: USD | L54: -1602.9371 | M54: USD | N54: 92.194654 | O54: 0 | P54: Strong buy
A55: ACP | B55: Miscellaneous | C55: abrdn Income Credit Strategies Fund of Benef Interest | D55: 5.425 | E55: USD | F55: 0.27726433 | G55: 295704 | H55: 0.35857787 | I55: 678798110 | J55: USD | K55: 15.238764 | L55: 0.356 | M55: USD | N55: -59.12744 | O55: 17.606285 | P55: Neutral
A56: ACP/PA | B56: Miscellaneous | C56: abrdn Income Credit Strategies Fund 5,250% Series A Perpetual Preferred Stock | D56: 19.8 | E56: USD | F56: -0.37735849 | G56: 321 | H56: 0.030231113 | P56: Neutral
A57: ACR | B57: Finance | C57: ACRES Commercial Realty Corp, | D57: 20.45 | E57: USD | F57: -0.77632217 | G57: 5963 | H57: 0.11663182 | I57: 150157875 | J57: USD | K57: 21.310963 | L57: 0.9596 | M57: USD | N57: 14.702367 | O57: 0 | P57: Buy
A58: ACR/PC | B58: Finance | C58: ACRES Commercial Realty Corp, 8,625% Fixed-to-Floating Series C Cumulative Redeemable Preferred Stock | D58: 24.8 | E58: USD | F58: 0.08071025 | G58: 10362 | H58: 0.90287278 | I58: 150157875 | J58: USD | K58: 25.844102 | L58: 0.9596 | M58: USD | N58: 14.702367 | O58: 0 | P58: Neutral
A59: ACR/PD | B59: Finance | C59: ACRES Commercial Realty Corp, 7,875% Series D Cumulative Redeemable Preferred Stock | D59: 21.905 | E59: USD | F59: 0.06852444 | G59: 2247 | H59: 0.40931944 | I59: 150157875 | J59: USD | K59: 22.82722 | L59: 0.9596 | M59: USD | N59: 14.702367 | O59: 0 | P59: Neutral
A60: ACT | B60: Finance | C60: Enact Holdings, Inc, | D60: 40.05 | E60: USD | F60: 1.0853104 | G60: 55524 | H60: 0.2368445 | I60: 5.7830503e+09 | J60: USD | K60: 9.2011855 | L60: 4.3527 | M60: USD | N60: 1.407171 | O60: 2.0570419 | P60: Buy
A61: ACTU | B61: Health technology | C61: Actuate Therapeutics, Inc, | D61: 6.18 | E61: USD | F61: 2.4875622 | G61: 24244 | H61: 0.27740559 | I61: 1.4364377e+08 | J61: USD | L61: -1.2096 | M61: USD | N61: 17.970975 | O61: 0 | P61: Strong buy
A62: ACV | B62: Miscellaneous | C62: Virtus Diversified Income & Convertible Fund | D62: 26.65 | E62: USD | F62: 1.4079148 | G62: 6891 | H62: 0.27295521 | I62: 272628720 | J62: USD | K62: 6.3951814 | L62: 4.1672 | M62: USD | N62: 130.80587 | O62: 8.2191781 | P62: Neutral
A63: ACVA | B63: Technology services | C63: ACV Auctions Inc, | D63: 8.385 | E63: USD | F63: 1.145959 | G63: 975276 | H63: 0.42918336 | I63: 1.4436557e+09 | J63: USD | L63: -0.4306 | M63: USD | N63: 8.4608844 | O63: 0 | P63: Buy
A64: AD | B64: Communications | C64: Array Digital Infrastructure, Inc, | D64: 54.18 | E64: USD | F64: 0.33333333 | G64: 15075 | H64: 0.077416631 | I64: 4.6814772e+09 | J64: USD | K64: 18.518012 | L64: 2.9258 | M64: USD | O64: 0 | P64: Buy
A65: ADACU | B65: Finance | C65: American Drive Acquisition Company Units Cons of 1 Shs A + 1/3 Red Wt | D65: 9.99 | E65: USD | F65: 0.1002004 | G65: 150383 | H65: 0.12707096 | I65: 229540000 | J65: USD | O65: 0 | P65: Neutral
A66: ADAM | B66: Finance | C66: Adamas Trust, Inc, | D66: 7.29 | E66: USD | F66: -2.016129 | G66: 232752 | H66: 0.25356131 | I66: 671889812 | J66: USD | K66: 38.571429 | L66: 0.189 | M66: USD | O66: 11.55914 | P66: Buy
A67: ADAMG | B67: Finance | C67: Adamas Trust, Inc, - 9,125% Senior Notes Due 2030 | D67: 25.15 | E67: USD | F67: -0.079459674 | G67: 3951 | H67: 0.20123563 | I67: 671889812 | J67: USD | K67: 133.06878 | L67: 0.189 | M67: USD | O67: 11.55914 | P67: Neutral
A68: ADAMH | B68: Finance | C68: Adamas Trust, Inc, - 9,875% Senior Notes Due 2030 | D68: 25.76 | E68: USD | F68: -0.038804812 | G68: 13588 | H68: 0.18191774 | I68: 671889812 | J68: USD | K68: 136.2963 | L68: 0.189 | M68: USD | O68: 11.55914 | P68: Neutral
A69: ADAMI | B69: Finance | C69: Adamas Trust, Inc, - 9,125% Senior Notes Due 2029 | D69: 25.19 | E69: USD | F69: 0.16024048 | G69: 496 | H69: 0.11044803 | I69: 671889812 | J69: USD | K69: 133.28042 | L69: 0.189 | M69: USD | O69: 11.55914 | P69: Neutral
A70: ADAML | B70: Finance | C70: Adamas Trust, Inc, - 6,875% Series F Fixed-to-Floating Rate Cumulative Redeemable Preferred Stock, $0,01 par value per share | D70: 22.8 | E70: USD | F70: 0.21978022 | G70: 1281 | H70: 0.22624914 | I70: 671889812 | J70: USD | K70: 120.63492 | L70: 0.189 | M70: USD | O70: 11.55914 | P70: Neutral
A71: ADAMM | B71: Finance | C71: Adamas Trust, Inc, - 7,875% Series E Fixed-to-Floating Rate Cumulative Redeemable Preferred Stock | D71: 24.9 | E71: USD | F71: 0.56542811 | G71: 8493 | H71: 0.58829641 | I71: 671889812 | J71: USD | K71: 131.74603 | L71: 0.189 | M71: USD | O71: 11.55914 | P71: Neutral
A72: ADAMN | B72: Finance | C72: Adamas Trust, Inc, - 8,00% Series D Fixed-to-Floating Rate Cumulative Redeemable Preferred Stock | D72: 21.91 | E72: USD | F72: 0.0456621 | G72: 1137 | H72: 0.059559043 | I72: 671889812 | J72: USD | K72: 115.92593 | L72: 0.189 | M72: USD | O72: 11.55914 | P72: Neutral
A73: ADAMZ | B73: Finance | C73: Adamas Trust, Inc, - 7,000% Series G Cumulative Redeemable Preferred Stock, $0,01 par value per share | D73: 19.2786 | E73: USD | F73: 0.14857143 | G73: 582 | H73: 0.089173536 | I73: 671889812 | J73: USD | K73: 102.00317 | L73: 0.189 | M73: USD | O73: 11.55914 | P73: Neutral
A74: ADBE | B74: Technology services | C74: Adobe Inc, | D74: 328.415 | E74: USD | F74: -1.4656466 | G74: 1845145 | H74: 0.5507833 | I74: 1.3747452e+11 | J74: USD | K74: 19.660036 | L74: 16.7047 | M74: USD | N74: 34.619786 | O74: 0 | P74: Buy
A75: ADC | B75: Finance | C75: Agree Realty Corporation | D75: 71.25 | E75: USD | F75: -1.2063228 | G75: 506064 | H75: 0.41297545 | I75: 8289068321 | J75: USD | K75: 41.678853 | L75: 1.7095 | M75: USD | N75: -5.4061532 | O75: 4.2720466 | P75: Buy
A76: ADC/PA | B76: Finance | C76: Agree Realty Corporation Depositary Shares, each representing 1/1,000th of a 4,250% Series A Cumulative Redeemable Preferred Stock | D76: 17.38 | E76: USD | F76: 0.46242775 | G76: 9705 | H76: 0.2365648 | I76: 8289068321 | J76: USD | K76: 10.166715 | L76: 1.7095 | M76: USD | N76: -5.4061532 | O76: 4.2720466 | P76: Neutral
A77: ADEA | B77: Technology services | C77: Adeia Inc, | D77: 18.51 | E77: USD | F77: 5.2901024 | G77: 494516 | H77: 0.35818647 | I77: 2.0270335e+09 | J77: USD | K77: 28.520801 | L77: 0.649 | M77: USD | N77: 77.46787 | O77: 1.1376564 | P77: Strong buy
A78: ADI | B78: Electronic technology | C78: Analog Devices, Inc, | D78: 280.1 | E78: USD | F78: 2.3233725 | G78: 709319 | H78: 0.23860831 | I78: 1.371521e+11 | J78: USD | K78: 61.300418 | L78: 4.5693 | M78: USD | N78: 39.354662 | O78: 1.4466282 | P78: Buy
A79: ADM | B79: Process industries | C79: Archer-Daniels-Midland Company | D79: 58.51 | E79: USD | F79: -0.91447925 | G79: 819398 | H79: 0.32277042 | I79: 2.8118136e+10 | J79: USD | K79: 23.804874 | L79: 2.4579 | M79: USD | N79: -29.882467 | O79: 3.4546994 | P79: Neutral
A80: ADMA | B80: Health technology | C80: ADMA Biologics Inc | D80: 17.8 | E80: USD | F80: -0.44742729 | G80: 339045 | H80: 0.18641798 | I80: 4.2363601e+09 | J80: USD | K80: 20.904287 | L80: 0.8515 | M80: USD | N80: 208.17952 | O80: 0 | P80: Strong buy
A81: ADNT | B81: Producer manufacturing | C81: Adient plc | D81: 19.47 | E81: USD | F81: 2.2584034 | G81: 211092 | H81: 0.22284987 | I81: 1.5410797e+09 | J81: USD | L81: -3.3366 | M81: USD | N81: -1555.1243 | O81: 0 | P81: Buy
A82: ADP | B82: Technology services | C82: Automatic Data Processing, Inc, | D82: 258.16 | E82: USD | F82: 2.0879469 | G82: 524827 | H82: 0.22167341 | I82: 1.0441249e+11 | J82: USD | K82: 25.461324 | L82: 10.1393 | M82: USD | N82: 8.3293268 | O82: 2.4992091 | P82: Neutral
A83: ADPT | B83: Health technology | C83: Adaptive Biotechnologies Corporation | D83: 15.425 | E83: USD | F83: -3.0483972 | G83: 672100 | H83: 0.36550197 | I83: 2.3548606e+09 | J83: USD | L83: -0.5381 | M83: USD | N83: 59.723054 | O83: 0 | P83: Strong buy
A84: ADSE | B84: Producer manufacturing | C84: ADS-TEC ENERGY PLC | D84: 12.19 | E84: USD | F84: -3.3306899 | G84: 3868 | H84: 0.087431002 | I84: 7.3289369e+08 | J84: USD | L84: -1.3926 | M84: USD | N84: 9.8990683 | O84: 0 | P84: Neutral
A85: ADSK | B85: Technology services | C85: Autodesk, Inc, | D85: 292.45 | E85: USD | F85: 1.9949081 | G85: 255191 | H85: 0.21401068 | I85: 6.1999402e+10 | J85: USD | K85: 56.773179 | L85: 5.1512 | M85: USD | N85: 2.334267 | O85: 0 | P85: Strong buy
A86: ADT | B86: Commercial services | C86: ADT Inc, | D86: 8.07 | E86: USD | F86: 0.74906367 | G86: 691283 | H86: 0.16819013 | I86: 6.173697e+09 | J86: USD | K86: 11.521987 | L86: 0.7004 | M86: USD | N86: -23.745237 | O86: 2.7465668 | P86: Buy
A87: ADTN | B87: Electronic technology | C87: ADTRAN Holdings, Inc, | D87: 8.825 | E87: USD | F87: 1.6705069 | G87: 244125 | H87: 0.24364042 | I87: 7.0702363e+08 | J87: USD | L87: -1.0855 | M87: USD | N87: 83.321297 | O87: 0 | P87: Buy
A88: ADUR | B88: Process industries | C88: Aduro Clean Technologies Inc, | D88: 12.31 | E88: USD | F88: 16.461684 | G88: 832243 | H88: 1.4968354 | I88: 3.8399206e+08 | J88: USD | L88: -0.396633 | M88: USD | N88: -37.762799 | O88: 0 | P88: Neutral
A89: ADUS | B89: Health services | C89: Addus HomeCare Corporation | D89: 108.495 | E89: USD | F89: 1.7967724 | G89: 30971 | H89: 0.19521355 | I89: 2.0053425e+09 | J89: USD | K89: 23.222389 | L89: 4.672 | M89: USD | N89: 6.9646046 | O89: 0 | P89: Buy
A90: ADX | B90: Miscellaneous | C90: Adams Diversified Equity Fund Inc Shs | D90: 23.47 | E90: USD | F90: 0.94623656 | G90: 171561 | H90: 0.71174792 | I90: 2821085250 | J90: USD | K90: 8.0004091 | L90: 2.9336 | M90: USD | N90: -42.299673 | O90: 6.6236559 | P90: Neutral
A91: ADXN | B91: Health technology | C91: Addex Therapeutics Ltd Sponsored ADR | D91: 8.09 | E91: USD | F91: 0 | G91: 631 | H91: 0.23839208 | I91: 10174339 | J91: USD | L91: -8.4372 | M91: USD | N91: -2086.9362 | O91: 0 | P91: Neutral
A92: AEAQU | B92: Finance | C92: Activate Energy Acquisition Corp, Units Cons of 1 Shs -A- + 1/2 Red Wt | D92: 10.1 | E92: USD | F92: 1.1011011 | G92: 3177 | H92: 0.19121851 | I92: 236213550 | J92: USD | O92: 0 | P92: Neutral
A93: AEBI | B93: Consumer durables | C93: Aebi Schmidt Holding AG | D93: 12.77 | E93: USD | F93: 1.4297061 | G93: 36424 | H93: 0.20497306 | I93: 9.8765456e+08 | J93: USD | O93: 0.39714059 | P93: Buy
A94: AEC | B94: Non-energy minerals | C94: Anfield Energy Inc, | D94: 5.975 | E94: USD | F94: 1.2711864 | G94: 40755 | H94: 0.31380729 | I94: 94869637 | J94: USD | L94: -0.712615 | M94: USD | N94: -230.65462 | O94: 0 | P94: Strong buy
A95: AEE | B95: Utilities | C95: Ameren Corporation | D95: 98.489 | E95: USD | F95: -2.3507833 | G95: 237421 | H95: 0.14647384 | I95: 2.6640773e+10 | J95: USD | K95: 18.946022 | L95: 5.1984 | M95: USD | N95: 22.323929 | O95: 2.8157843 | P95: Buy
A96: AEFC | B96: Finance | C96: Aegon Funding Company LLC 5,10% Subordinated Notes due 2049 | D96: 19.88 | E96: USD | F96: 0.25214322 | G96: 19816 | H96: 0.37949181 | P96: Neutral
A97: AEG | B97: Finance | C97: Aegon Ltd, Sponsored ADR | D97: 7.845 | E97: USD | F97: 1.0953608 | G97: 966971 | H97: 0.32605645 | I97: 1.1626594e+10 | J97: USD | K97: 8.6560741 | L97: 0.9063 | M97: USD | O97: 4.8325129 | P97: Buy
A98: AEHR | B98: Electronic technology | C98: Aehr Test Systems | D98: 23.5607 | E98: USD | F98: 6.3208484 | G98: 294526 | H98: 0.58621472 | I98: 7.0697626e+08 | J98: USD | L98: -0.2232 | M98: USD | N98: -122.63921 | O98: 0 | P98: Neutral
A99: AEIS | B99: Electronic technology | C99: Advanced Energy Industries, Inc, | D99: 228.33 | E99: USD | F99: 2.8559845 | G99: 208544 | H99: 0.73691761 | I99: 8.6184273e+09 | J99: USD | K99: 60.069454 | L99: 3.8011 | M99: USD | N99: 234.33899 | O99: 0.1801883 | P99: Buy
A100: AEM | B100: Non-energy minerals | C100: Agnico Eagle Mines Limited | D100: 178.6146 | E100: USD | F100: 4.7900264 | G100: 1287470 | H100: 0.50463392 | I100: 8.967285e+10 | J100: USD | K100: 26.024359 | L100: 6.863362 | M100: USD | N100: 240.72262 | O100: 0.95552612 | P100: Buy
...

Sheet Tickers_500
A1: Ticker | B1: Sector | C1: Index
A2: AA | B2: =VLOOKUP(A2,Tickers!A:B,2,FALSE) -> Non-energy minerals | C2: =VLOOKUP(B2,Match_Sector!A:B,2,FALSE) -> XLB (Materials)
A3: AAL | B3: =VLOOKUP(A3,Tickers!A:B,2,FALSE) -> Transportation | C3: =VLOOKUP(B3,Match_Sector!A:B,2,FALSE) -> XLI (Industrials)
A4: AAOI | B4: =VLOOKUP(A4,Tickers!A:B,2,FALSE) -> Electronic technology | C4: =VLOOKUP(B4,Match_Sector!A:B,2,FALSE) -> XLK (Technology)
A5: ABR | B5: =VLOOKUP(A5,Tickers!A:B,2,FALSE) -> Finance | C5: =VLOOKUP(B5,Match_Sector!A:B,2,FALSE) -> XLF (Financials)
A6: ACHC | B6: =VLOOKUP(A6,Tickers!A:B,2,FALSE) -> Health services | C6: =VLOOKUP(B6,Match_Sector!A:B,2,FALSE) -> XLV (Health Care)
A7: ACHR | B7: =VLOOKUP(A7,Tickers!A:B,2,FALSE) -> Electronic technology | C7: =VLOOKUP(B7,Match_Sector!A:B,2,FALSE) -> XLK (Technology)
A8: ACI | B8: =VLOOKUP(A8,Tickers!A:B,2,FALSE) -> Retail trade | C8: =VLOOKUP(B8,Match_Sector!A:B,2,FALSE) -> XLY (Consumer Discretionary)*
A9: ACVA | B9: =VLOOKUP(A9,Tickers!A:B,2,FALSE) -> Technology services | C9: =VLOOKUP(B9,Match_Sector!A:B,2,FALSE) -> XLK (Technology)
A10: ADM | B10: =VLOOKUP(A10,Tickers!A:B,2,FALSE) -> Process industries | C10: =VLOOKUP(B10,Match_Sector!A:B,2,FALSE) -> XLB (Materials)
A11: ADMA | B11: =VLOOKUP(A11,Tickers!A:B,2,FALSE) -> Health technology | C11: =VLOOKUP(B11,Match_Sector!A:B,2,FALSE) -> XLV (Health Care)
A12: ADPT | B12: =VLOOKUP(A12,Tickers!A:B,2,FALSE) -> Health technology | C12: =VLOOKUP(B12,Match_Sector!A:B,2,FALSE) -> XLV (Health Care)
A13: ADT | B13: =VLOOKUP(A13,Tickers!A:B,2,FALSE) -> Commercial services | C13: =VLOOKUP(B13,Match_Sector!A:B,2,FALSE) -> XLI (Industrials)
... A493: ZM | B493: =VLOOKUP(A493,Tickers!A:B,2,FALSE) -> Technology services | C493: =VLOOKUP(B493,Match_Sector!A:B,2,FALSE) -> XLK (Technology)

Sheet Match_Sector
A1: TradingView sector | B1: Closest SPDR sector ETF
A2: Commercial Services | B2: XLI (Industrials)
A3: Communications | B3: XLC (Communication Services)
A4: Consumer Durables | B4: XLY (Consumer Discretionary)
A5: Consumer non-durables | B5: XLY (Consumer Discretionary)
A6: Consumer Services | B6: XLY (Consumer Discretionary)
A7: Distribution services | B7: XLI (Industrials)
A8: Electronic Technology | B8: XLK (Technology)
A9: Energy Minerals | B9: XLE (Energy)
A10: Finance | B10: XLF (Financials)
A11: Health Services | B11: XLV (Health Care)
A12: Health Technology | B12: XLV (Health Care)
... A20: Utilities | B20: XLU (Utilities)

Sheet Match_Index
A1: Closest SPDR sector ETF | B1: TradingView sector
A2: XLB (Materials) | B2: Non-energy minerals
A3: XLB (Materials) | B3: Process Industries
A4: XLC (Communication Services) | B4: Communications
A5: XLE (Energy) | B5: Energy Minerals
A6: XLF (Financials) | B6: Finance
A7: XLI (Industrials) | B7: Commercial Services
A8: XLI (Industrials) | B8: Distribution services
A9: XLI (Industrials) | B9: Industrial services
A10: XLI (Industrials) | B10: Producer Manufacturing
A11: XLI (Industrials) | B11: Transportation
A12: XLK (Technology) | B12: Electronic Technology
... A19: XLY (Consumer Discretionary)* | B19: Retail Trade
